pytest_cfg_fetcher/fetch.py
pytest_cfg_fetcher-0.1.1.dist-info/METADATA
pytest_cfg_fetcher-0.1.1.dist-info/WHEEL
pytest_cfg_fetcher-0.1.1.dist-info/RECORD
