Metadata-Version: 2.1
Name: pytest-cfg-fetcher
Version: 0.1.1
Summary: Pass config options to your unit tests.
Home-page: https://github.com/BobBorges/pytest-cfg-fetcher
License: MIT
Author: BobBorges
Requires-Python: >=3.8,<4.0
Classifier: License :: OSI Approved :: MIT License
Classifier: Programming Language :: Python :: 3
Classifier: Programming Language :: Python :: 3.8
Classifier: Programming Language :: Python :: 3.9
Classifier: Programming Language :: Python :: 3.10
Classifier: Programming Language :: Python :: 3.11
Classifier: Programming Language :: Python :: 3.12
Project-URL: Repository, https://github.com/BobBorges/pytest-cfg-fetcher
